git_clone.py
vercel_deploy.py
vercel_deploy-1.9.dist-info/METADATA
vercel_deploy-1.9.dist-info/WHEEL
vercel_deploy-1.9.dist-info/entry_points.txt
vercel_deploy-1.9.dist-info/top_level.txt
vercel_deploy-1.9.dist-info/RECORD
