Metadata-Version: 2.1
Name: vercel-deploy
Version: 1.9
Summary: UNKNOWN
Home-page: UNKNOWN
License: UNKNOWN
Platform: UNKNOWN
Requires-Dist: python-dotenv
Requires-Dist: PyGithub
